pyvjoystick/__init__.py
pyvjoystick/resource_loader.py
pyvjoystick/utils.py
pyvjoystick/vigem/__init__.py
pyvjoystick/vigem/_sdk.py
pyvjoystick/vigem/client/__init__.py
pyvjoystick/vigem/client/x64/__init__.py
pyvjoystick/vigem/client/x64/ViGEmClient.dll
pyvjoystick/vigem/client/x86/__init__.py
pyvjoystick/vigem/client/x86/ViGEmClient.dll
pyvjoystick/vigem/constants.py
pyvjoystick/vigem/device.py
pyvjoystick/vigem/exceptions.py
pyvjoystick/vigem/utils.py
pyvjoystick/vigem/vbus.py
pyvjoystick/vigem/vds4.py
pyvjoystick/vigem/vx360.py
pyvjoystick/vjoy/__init__.py
pyvjoystick/vjoy/_sdk.py
pyvjoystick/vjoy/constants.py
pyvjoystick/vjoy/exceptions.py
pyvjoystick/vjoy/utils.py
pyvjoystick/vjoy/vjoydevice.py
pyvjoystick-1.1.2.1.dist-info/LICENSE
pyvjoystick-1.1.2.1.dist-info/WHEEL
pyvjoystick-1.1.2.1.dist-info/METADATA
pyvjoystick-1.1.2.1.dist-info/RECORD
