Metadata-Version: 2.1
Name: pyvjoystick
Version: 1.1.2.1
Summary: Python bindings for vJoy
Home-page: https://github.com/fsadannn/pyvjoystick
License: MIT
Author: fsadannn
Author-email: fsadannn@gmail.com
Requires-Python: >=3.8,<4
Classifier: Intended Audience :: Developers
Classifier: License :: OSI Approved :: MIT License
Classifier: Operating System :: Microsoft :: Windows
Classifier: Programming Language :: Python :: 3
Classifier: Programming Language :: Python :: 3.10
Classifier: Programming Language :: Python :: 3.8
Classifier: Programming Language :: Python :: 3.9
Classifier: Topic :: Software Development
Classifier: Topic :: System :: Hardware :: Universal Serial Bus (USB) :: Human Interface Device (HID)
Project-URL: Repository, https://github.com/fsadannn/pyvjoystick
